iostuff/__init__.py
iostuff/common/__init__.py
iostuff/common/binary.py
iostuff/common/utf8.py
iostuff/readers/__init__.py
iostuff/readers/binary.py
iostuff/readers/csv.py
iostuff/readers/json.py
iostuff/readers/text.py
iostuff/writers/__init__.py
iostuff/writers/binary.py
iostuff/writers/csv.py
iostuff/writers/json.py
iostuff/writers/text.py
iostuff_tools-1.1.1.dist-info/METADATA
iostuff_tools-1.1.1.dist-info/WHEEL
iostuff_tools-1.1.1.dist-info/licenses/LICENSE
iostuff_tools-1.1.1.dist-info/RECORD
