Metadata-Version: 2.1
Name: iostuff_tools
Version: 1.1.1
Summary: Python I/O library
Author-email: bqio <dmitry.mikhaltsov98@gmail.com>
License-File: LICENSE
Classifier: License :: OSI Approved :: MIT License
Classifier: Operating System :: OS Independent
Classifier: Programming Language :: Python :: 3
Requires-Python: >=3.7
Requires-Dist: jsonpickle<=3.0.2
